cotests/__init__.py
cotests/batch.py
cotests/module.py
cotests/typ.py
cotests/case/__init__.py
cotests/case/abstract.py
cotests/case/case.py
cotests/cases/__init__.py
cotests/cases/abstract.py
cotests/cases/cases.py
cotests/cases/group.py
cotests/cases/unit_case.py
cotests/cases/runner/__init__.py
cotests/cases/runner/abstract.py
cotests/cases/runner/case.py
cotests/cases/runner/group.py
cotests/cases/runner/unit.py
cotests/cases/runner/utils/__init__.py
cotests/cases/runner/utils/printer.py
cotests/cases/runner/utils/progress_bar.py
cotests/cases/utils/__init__.py
cotests/cases/utils/args.py
cotests/cases/utils/case_ext.py
cotests/cases/utils/ttr.py
cotests/exceptions/__init__.py
cotests/exceptions/exc.py
cotests/logger/__init__.py
cotests-0.4.dist-info/METADATA
cotests-0.4.dist-info/WHEEL
cotests-0.4.dist-info/top_level.txt
cotests-0.4.dist-info/RECORD
