Metadata-Version: 2.1
Name: cotests
Version: 0.4
Summary: Tests & benchs for python
Author: iSergium
License: apache2.0
Project-URL: Homepage, https://github.com/coddism/cotests
Keywords: python,tests,benchmark
Requires-Python: >=3.7
Provides-Extra: dev
Requires-Dist: typing-extensions ; (python_version < "3.11") and extra == 'dev'
